zefirkagram/__init__.py
zefirkagram/bot.py
zefirkagram-0.1.dist-info/METADATA
zefirkagram-0.1.dist-info/WHEEL
zefirkagram-0.1.dist-info/top_level.txt
zefirkagram-0.1.dist-info/RECORD
