Metadata-Version: 2.1
Name: zefirkagram
Version: 0.1
Summary: A simple Telegram bot to send messages and pictures to a Telegram channel
Home-page: https://github.com/resonaura/zefirkagram
Author: Resonaura
Author-email: resonaura@gmail.com
Classifier: Programming Language :: Python :: 3
Classifier: License :: OSI Approved :: MIT License
Classifier: Operating System :: OS Independent
Requires-Python: >=3.6
Requires-Dist: requests
